scilog/__init__.py
scilog/scilog.py
scilog-1.7.2.data/scripts/gitdiffuntracked
scilog-1.7.2.data/scripts/scilog
scilog-1.7.2.dist-info/LICENSE
scilog-1.7.2.dist-info/METADATA
scilog-1.7.2.dist-info/WHEEL
scilog-1.7.2.dist-info/top_level.txt
scilog-1.7.2.dist-info/RECORD
