Metadata-Version: 2.1
Name: scilog
Version: 1.7.2
Summary: Record-keeping for computational experiments
Home-page: https://github.com/soerenwolfers/scilog
Author: Soeren Wolfers
Author-email: soeren.wolfers@gmail.com
License: UNKNOWN
Platform: UNKNOWN
Requires-Python: >=3.6
Requires-Dist: swutil
Requires-Dist: IPython
Requires-Dist: matplotlib
Requires-Dist: numpy
Requires-Dist: argcomplete
